blynclight/__init__.py
blynclight/__main__.py
blynclight/__version__.py
blynclight/blynclight.py
blynclight/constants.py
blynclight/effects/__init__.py
blynclight/effects/gradient.py
blynclight/effects/spectrum.py
blynclight/exceptions.py
blynclight/oldlight.py
blynclight-0.12.0.dist-info/entry_points.txt
blynclight-0.12.0.dist-info/LICENSE
blynclight-0.12.0.dist-info/WHEEL
blynclight-0.12.0.dist-info/METADATA
blynclight-0.12.0.dist-info/RECORD
