Metadata-Version: 2.1
Name: blynclight
Version: 0.12.0
Summary: Python language bindings for Embrava BlyncLight devices.
Home-page: https://github.com/JnyJny/blynclight.git
License: Apache-2.0
Author: Erik O'Shaughnessy
Author-email: erik.oshaughnessy@gmail.com
Requires-Python: >=3.6,<4.0
Classifier: Development Status :: 4 - Beta
Classifier: Environment :: Console
Classifier: Intended Audience :: Developers
Classifier: License :: OSI Approved :: Apache Software License
Classifier: Programming Language :: Python :: 3
Classifier: Programming Language :: Python :: 3.6
Classifier: Programming Language :: Python :: 3.7
Classifier: Programming Language :: Python :: 3.8
Classifier: Programming Language :: Python :: 3.9
Classifier: Topic :: Artistic Software
Classifier: Topic :: Multimedia :: Sound/Audio
Classifier: Topic :: System :: Hardware
Classifier: Topic :: Utilities
Requires-Dist: bitvector-for-humans (>=0,<1)
Requires-Dist: hidapi (>=0,<1)
Requires-Dist: loguru (>=0.5.1,<0.6.0)
Requires-Dist: typer (>=0,<1)
Project-URL: Repository, https://github.com/JnyJny/blynclight.git
